AUTHORS.rst
CONTRIBUTING.rst
HISTORY.rst
LICENSE
MANIFEST.in
README.rst
setup.py
appengine_toolkit/__init__.py
appengine_toolkit/models.py
appengine_toolkit/settings.py
appengine_toolkit.egg-info/PKG-INFO
appengine_toolkit.egg-info/SOURCES.txt
appengine_toolkit.egg-info/dependency_links.txt
appengine_toolkit.egg-info/not-zip-safe
appengine_toolkit.egg-info/top_level.txt
appengine_toolkit/management/__init__.py
appengine_toolkit/management/commands/__init__.py
appengine_toolkit/management/commands/_utils.py
appengine_toolkit/management/commands/collectdeps.py
appengine_toolkit/static/js/appengine_toolkit.js
appengine_toolkit/templates/appengine_toolkit/base.html